{
    "bsonType": "object",
    "properties": {
        "Description1": {
            "bsonType": "string"
        },
        "Description2": {
            "bsonType": "string"
        },
        "InventoryCode": {
            "bsonType": "string"
        },
        "Public": {
            "bsonType": "string"
        },
        "QtyRequired": {
            "bsonType": "double"
        },
        "Value": {
            "bsonType": "double"
        },
        "_id": {
            "bsonType": "objectId"
        },
        "partition": {
            "bsonType": "string"
        }
    },
    "required": [
        "_id",
        "Public",
        "Value",
        "QtyRequired"
    ],
    "title": "ScheduleSparePart"
}
